__init__.py
eurlex.py
utils.py
eurlex_parser.egg-info/PKG-INFO
eurlex_parser.egg-info/SOURCES.txt
eurlex_parser.egg-info/dependency_links.txt
eurlex_parser.egg-info/requires.txt
eurlex_parser.egg-info/top_level.txt
eurlex_parser-0.0.13.dist-info/LICENSE
eurlex_parser-0.0.13.dist-info/METADATA
eurlex_parser-0.0.13.dist-info/WHEEL
eurlex_parser-0.0.13.dist-info/top_level.txt
eurlex_parser-0.0.13.dist-info/RECORD
