Metadata-Version: 2.1
Name: eurlex-parser
Version: 0.0.13
Summary: Eurlex parser for fetching and parsing Eurlex data.
Home-page: https://github.com/noworneverev/eurlex-parser
Author: Yan-Ying Liao
Author-email: n9102125@gmail.com
Classifier: Intended Audience :: Developers
Classifier: Programming Language :: Python :: 3
Classifier: Operating System :: Unix
Classifier: Operating System :: MacOS :: MacOS X
Classifier: Operating System :: Microsoft :: Windows
Requires-Python: >=3.6
License-File: LICENSE
Requires-Dist: requests ==2.32.3
Requires-Dist: bs4 ==0.0.2
Requires-Dist: lxml ==5.2.2
Requires-Dist: pandas ==2.2.2
